namefully/__init__.py
namefully/_config.py
namefully/_constants.py
namefully/_errors.py
namefully/_full_name.py
namefully/_name.py
namefully/_namefully.py
namefully/_parser.py
namefully/_types.py
namefully/_utils.py
namefully/_validators.py
namefully/_version.py
namefully/builder.py
namefully-1.2.0.dist-info/METADATA
namefully-1.2.0.dist-info/WHEEL
namefully-1.2.0.dist-info/licenses/LICENSE
namefully-1.2.0.dist-info/RECORD
