Metadata-Version: 2.4
Name: namefully
Version: 1.2.0
Summary: Handle personal names in a particular order, way, or shape.
Project-URL: Repository, https://github.com/ralflorent/namefully-python
Project-URL: Homepage, https://github.com/ralflorent/namefully-python/blob/main/README.md
Project-URL: Changelog, https://github.com/ralflorent/namefully-python/blob/main/CHANGELOG.md
Author-email: Ralph Florent <ralflornt@gmail.com>
License-Expression: MIT
License-File: LICENSE
Keywords: family,format,human,name,parse,personal
Classifier: Intended Audience :: Developers
Classifier: License :: OSI Approved :: MIT License
Classifier: Operating System :: MacOS
Classifier: Operating System :: Microsoft :: Windows
Classifier: Operating System :: OS Independent
Classifier: Operating System :: POSIX
Classifier: Operating System :: POSIX :: Linux
Classifier: Programming Language :: Python :: 3.7
Classifier: Programming Language :: Python :: 3.8
Classifier: Programming Language :: Python :: 3.9
Classifier: Programming Language :: Python :: 3.10
Classifier: Programming Language :: Python :: 3.11
Classifier: Programming Language :: Python :: 3.12
Classifier: Topic :: Software Development :: Libraries :: Python Modules
Classifier: Typing :: Typed
Requires-Python: >=3.7
